newio_rethinkdb
