Metadata-Version: 1.1
Name: newio-rethinkdb
Version: 0.1.2
Summary: Newio + RethinkDB: Async RethinkDB driver
Home-page: https://github.com/guyskk/newio-rethinkdb
Author: guyskk
Author-email: guyskk@qq.com
License: MIT
Keywords: newio rethinkdb async driver
Platform: UNKNOWN
Classifier: Intended Audience :: Developers
Classifier: License :: OSI Approved :: MIT License
Classifier: Operating System :: OS Independent
Classifier: Programming Language :: Python :: 3 :: Only
Classifier: Topic :: Software Development :: Libraries :: Python Modules
